virtualizorenduser/__init__.py
virtualizorenduser/api.py
virtualizorenduser-0.7.dist-info/METADATA
virtualizorenduser-0.7.dist-info/WHEEL
virtualizorenduser-0.7.dist-info/RECORD
