Metadata-Version: 2.3
Name: virtualizorenduser
Version: 0.7
Summary: Virtualizor Enduser API library, in Python.
Author: Hendra Manudinata
Author-email: manoedinata@gmail.com
Requires-Python: >=3.10,<4.0
Classifier: Programming Language :: Python :: 3
Classifier: Programming Language :: Python :: 3.10
Classifier: Programming Language :: Python :: 3.11
Classifier: Programming Language :: Python :: 3.12
Classifier: Programming Language :: Python :: 3.13
Requires-Dist: requests (>=2.32.3,<3.0.0)
